LICENSE
README.md
setup.py
tap_deputy/__init__.py
tap_deputy/client.py
tap_deputy/discover.py
tap_deputy/sync.py
tap_deputy/utils.py
tap_deputy.egg-info/PKG-INFO
tap_deputy.egg-info/SOURCES.txt
tap_deputy.egg-info/dependency_links.txt
tap_deputy.egg-info/entry_points.txt
tap_deputy.egg-info/requires.txt
tap_deputy.egg-info/top_level.txt