Metadata-Version: 2.1
Name: tap-deputy
Version: 1.1.0
Summary: Singer.io tap for extracting data from the Deputy API
Home-page: https://www.deputy.com
Author: Deputy
License: UNKNOWN
Platform: UNKNOWN
Classifier: Programming Language :: Python :: 3 :: Only
Requires-Python: >=3.5.3
Provides-Extra: dev
